conctl/__init__.py
conctl/base.py
conctl/containerd.py
conctl/docker.py
conctl/bin/conctl.py
conctl_py35-0.1.0.dist-info/LICENSE
conctl_py35-0.1.0.dist-info/METADATA
conctl_py35-0.1.0.dist-info/WHEEL
conctl_py35-0.1.0.dist-info/entry_points.txt
conctl_py35-0.1.0.dist-info/top_level.txt
conctl_py35-0.1.0.dist-info/RECORD
